MANIFEST.in
README.md
VERSION.txt
requirements.txt
requirements_dev.txt
setup.cfg
setup.py
html_to_draftjs/__init__.py
html_to_draftjs/converter.py
html_to_draftjs/types.py
html_to_draftjs.egg-info/PKG-INFO
html_to_draftjs.egg-info/SOURCES.txt
html_to_draftjs.egg-info/dependency_links.txt
html_to_draftjs.egg-info/not-zip-safe
html_to_draftjs.egg-info/requires.txt
html_to_draftjs.egg-info/top_level.txt