Metadata-Version: 2.1
Name: html-to-draftjs
Version: 1.0.1
Summary: Convert basic HTML into DraftJS JSON format.
Home-page: https://github.com/NyanKiyoshi/html-to-draftjs/
Author: NyanKiyoshi
Author-email: hello@vanille.bid
License: UNKNOWN
Platform: UNKNOWN
Classifier: Programming Language :: Python
Classifier: Programming Language :: Python :: 3.5
Classifier: Programming Language :: Python :: 3.6
Classifier: Programming Language :: Python :: 3.7
Classifier: Programming Language :: Python :: 3.8
Classifier: Environment :: Web Environment
Classifier: Intended Audience :: Developers
Classifier: Operating System :: OS Independent
Classifier: License :: OSI Approved :: MIT License
Classifier: Topic :: Software Development :: Libraries :: Python Modules
Provides-Extra: dev
